solve_ivp_pint/__init__.py
solve_ivp_pint/solve_ivp_pint.py
solve_ivp_pint-1.0.1.dist-info/METADATA
solve_ivp_pint-1.0.1.dist-info/WHEEL
solve_ivp_pint-1.0.1.dist-info/licenses/LICENSE
solve_ivp_pint-1.0.1.dist-info/RECORD
