Metadata-Version: 2.4
Name: solve_ivp_pint
Version: 1.0.1
Summary: ODE solver processing pint (using 'solve_ivp' function)
Project-URL: Repository, https://github.com/BioDisCo/solve_ivp_pint/
Author-email: Alexandra Loudieres <alexandra.loudieres@ens-paris-saclay.fr>, Matthias Függer <mfuegger@lmf.cnrs.fr>, Thomas Nowak <thomas@thomasnowak.net>
Maintainer-email: Alexandra Loudieres <alexandra.loudieres@ens-paris-saclay.fr>, Matthias Függer <mfuegger@lmf.cnrs.fr>, Thomas Nowak <thomas@thomasnowak.net>
License:                                  Apache License
License-File: LICENSE
Keywords: ODE solver,pint,solve_ivp
Classifier: Development Status :: 4 - Beta
Classifier: Programming Language :: Python
Requires-Python: >=3.12
Requires-Dist: numpy
Requires-Dist: pint
Requires-Dist: scipy
